[
  {
    "title": "The Alchemist",
    "authors": ["Paulo Coelho"],
    "publisher": "HarperCollins",
    "publishedDate": "2015-01-01",
    "description": "A tale about following your dreams, The Alchemist tells the story of a young shepherd named Santiago who seeks treasure in Egypt.",
    "pageCount": 208,
    "categories": ["Fiction", "Philosophy"],
    "language": "en",
    "cover": "https://m.media-amazon.com/images/I/71zHDXu1TaL._AC_UF1000,1000_QL80_.jpg"
  },
  {
    "title": "The White Tiger",
    "authors": ["Aravind Adiga"],
    "publisher": "Free Press",
    "publishedDate": "2008-04-22",
    "description": "A gripping story of class struggle in modern India, narrated by a man who rises from poor beginnings to become a successful entrepreneur.",
    "pageCount": 304,
    "categories": ["Fiction"],
    "language": "en",
    "cover": "https://www.crossword.in/cdn/shop/products/81DzJ5OV9ZL.jpg?v=1685693149"
  },
  {
    "title": "2 States",
    "authors": ["Chetan Bhagat"],
    "publisher": "Rupa Publications",
    "publishedDate": "2009-10-01",
    "description": "A story about a couple from different cultural backgrounds who struggle to convince their families to accept their love.",
    "pageCount": 300,
    "categories": ["Romance", "Fiction"],
    "language": "en",
    "cover": "https://www.crossword.in/cdn/shop/products/714GGM7WK7L.jpg?v=1685357582"
  },
  {
    "title": "Rich Dad Poor Dad",
    "authors": ["Robert Kiyosaki"],
    "publisher": "Platinum Press",
    "publishedDate": "2000-04-01",
    "description": "A personal finance classic that contrasts the financial philosophies of the author's two 'dads'—his biological father and his best friend's father.",
    "pageCount": 336,
    "categories": ["Business", "Self-help"],
    "language": "en",
    "cover": "https://www.crossword.in/cdn/shop/products/714GGM7WK7L.jpg?v=1685357582"
  },
  {
    "title": "The Kite Runner",
    "authors": ["Khaled Hosseini"],
    "publisher": "Riverhead Books",
    "publishedDate": "2003-05-29",
    "description": "A powerful story of friendship and redemption set against the backdrop of a changing Afghanistan.",
    "pageCount": 371,
    "categories": ["Fiction", "Historical"],
    "language": "en",
    "cover": "https://www.crossword.in/cdn/shop/products/714GGM7WK7L.jpg?v=1685357582"
  },
  {
    "title": "The Subtle Art of Not Giving a F*ck",
    "authors": ["Mark Manson"],
    "publisher": "HarperOne",
    "publishedDate": "2016-09-13",
    "description": "A counterintuitive approach to living a good life, emphasizing the importance of choosing what to care about.",
    "pageCount": 224,
    "categories": ["Self-help"],
    "language": "en",
    "cover": "https://www.crossword.in/cdn/shop/products/714GGM7WK7L.jpg?v=1685357582"
  },
  {
    "title": "Midnight's Children",
    "authors": ["Salman Rushdie"],
    "publisher": "Random House",
    "publishedDate": "1981-02-11",
    "description": "A magical realist novel that intertwines the life of its protagonist with the history of India, exploring identity and nationalism.",
    "pageCount": 605,
    "categories": ["Fiction", "Historical"],
    "language": "en",
    "cover": "https://www.crossword.in/cdn/shop/products/714GGM7WK7L.jpg?v=1685357582"
  },
  {
    "title": "The God of Small Things",
    "authors": ["Arundhati Roy"],
    "publisher": "Random House India",
    "publishedDate": "1997-06-01",
    "description": "A poignant tale of love and loss in Kerala, narrated through the eyes of fraternal twins and their family’s tragic history.",
    "pageCount": 341,
    "categories": ["Fiction", "Literary"],
    "language": "en",
    "cover": "https://www.crossword.in/cdn/shop/products/714GGM7WK7L.jpg?v=1685357582"
  },
  {
    "title": "A Suitable Boy",
    "authors": ["Vikram Seth"],
    "publisher": "Phoenix",
    "publishedDate": "1993-09-01",
    "description": "A sprawling novel about family and love in post-independence India, centered around the quest to find a suitable match for a young girl.",
    "pageCount": 1474,
    "categories": ["Fiction", "Historical"],
    "language": "en",
    "cover": "https://www.crossword.in/cdn/shop/products/714GGM7WK7L.jpg?v=1685357582"
  },
  {
    "title": "When a Moth Meets a Flame",
    "authors": ["Tuhin A. Sinha"],
    "publisher": "Srishti Publishers",
    "publishedDate": "2013-12-10",
    "description": "A romantic thriller that delves into the complexities of love, betrayal, and the consequences of choices made.",
    "pageCount": 280,
    "categories": ["Romance", "Thriller"],
    "language": "en",
    "cover": "https://www.crossword.in/cdn/shop/products/714GGM7WK7L.jpg?v=1685357582"
  },
  {
    "title": "One Indian Girl",
    "authors": ["Chetan Bhagat"],
    "publisher": "Rupa Publications",
    "publishedDate": "2016-10-01",
    "description": "A story that tackles the expectations placed on women in Indian society through the eyes of a successful young woman.",
    "pageCount": 300,
    "categories": ["Fiction", "Women"],
    "language": "en",
    "cover": "https://www.crossword.in/cdn/shop/products/714GGM7WK7L.jpg?v=1685357582"
  },
  {
    "title": "The 5 AM Club",
    "authors": ["Robin Sharma"],
    "publisher": "HarperCollins",
    "publishedDate": "2018-12-31",
    "description": "A revolutionary method to wake up early and maximize productivity, success, and personal growth.",
    "pageCount": 336,
    "categories": ["Self-help", "Motivation"],
    "language": "en",
    "cover": "https://www.crossword.in/cdn/shop/products/714GGM7WK7L.jpg?v=1685357582"
  },
  {
    "title": "The Silent Patient",
    "authors": ["Alex Michaelides"],
    "publisher": "Celadon Books",
    "publishedDate": "2019-02-05",
    "description": "A psychological thriller about a woman who shoots her husband and then stops speaking, unraveling a gripping mystery.",
    "pageCount": 336,
    "categories": ["Thriller", "Mystery"],
    "language": "en",
    "cover": "https://www.crossword.in/cdn/shop/products/714GGM7WK7L.jpg?v=1685357582"
  },
  {
    "title": "The Power of Now",
    "authors": ["Eckhart Tolle"],
    "publisher": "New World Library",
    "publishedDate": "1997-09-01",
    "description": "A guide to spiritual enlightenment that emphasizes living in the present moment.",
    "pageCount": 229,
    "categories": ["Self-help", "Spirituality"],
    "language": "en",
    "cover": "https://www.crossword.in/cdn/shop/products/714GGM7WK7L.jpg?v=1685357582"
  },
  {
    "title": "The Night Circus",
    "authors": ["Erin Morgenstern"],
    "publisher": "Doubleday",
    "publishedDate": "2011-09-13",
    "description": "A mesmerizing tale of a magical competition between two young illusionists at a mysterious circus that appears only at night.",
    "pageCount": 512,
    "categories": ["Fantasy", "Fiction"],
    "language": "en",
    "cover": "https://www.crossword.in/cdn/shop/products/714GGM7WK7L.jpg?v=1685357582"
  },
  {
    "title": "The Dutch House",
    "authors": ["Ann Patchett"],
    "publisher": "HarperCollins",
    "publishedDate": "2019-09-24",
    "description": "A rich family saga that explores themes of love, loss, and the ties that bind us to our past.",
    "pageCount": 352,
    "categories": ["Fiction", "Literary"],
    "language": "en",
    "cover": "https://www.crossword.in/cdn/shop/products/714GGM7WK7L.jpg?v=1685357582"
  },
  {
    "title": "Educated",
    "authors": ["Tara Westover"],
    "publisher": "Random House",
    "publishedDate": "2018-02-20",
    "description": "A memoir about a woman who grows up in a strict and abusive household in rural Idaho and eventually escapes to learn about the wider world through education.",
    "pageCount": 334,
    "categories": ["Memoir", "Biography"],
    "language": "en",
    "cover": "https://www.crossword.in/cdn/shop/products/714GGM7WK7L.jpg?v=1685357582"
  },
  {
    "title": "The Girl on the Train",
    "authors": ["Paula Hawkins"],
    "publisher": "Riverhead Books",
    "publishedDate": "2015-01-13",
    "description": "A psychological thriller that follows a woman who becomes entangled in a missing persons investigation that unveils dark secrets.",
    "pageCount": 336,
    "categories": ["Thriller", "Mystery"],
    "language": "en",
    "cover": "https://www.crossword.in/cdn/shop/products/714GGM7WK7L.jpg?v=1685357582"
  },
  {
    "title": "To Kill a Mockingbird",
    "authors": ["Harper Lee"],
    "publisher": "J.B. Lippincott & Co.",
    "publishedDate": "1960-07-11",
    "description": "A classic novel about racial injustice and moral growth in the American South, told through the eyes of a young girl.",
    "pageCount": 281,
    "categories": ["Fiction", "Classic"],
    "language": "en",
    "cover": "https://www.crossword.in/cdn/shop/products/714GGM7WK7L.jpg?v=1685357582"
  },
  {
    "title": "Becoming",
    "authors": ["Michelle Obama"],
    "publisher": "Crown Publishing Group",
    "publishedDate": "2018-11-13",
    "description": "A deeply personal memoir by the former First Lady of the United States, sharing her experiences and insights.",
    "pageCount": 448,
    "categories": ["Memoir", "Biography"],
    "language": "en",
    "cover": "https://www.crossword.in/cdn/shop/products/714GGM7WK7L.jpg?v=1685357582"
  },
  {
    "title": "Pride and Prejudice",
    "authors": ["Jane Austen"],
    "publisher": "T. Egerton, Whitehall",
    "publishedDate": "1813-01-28",
    "description": "A romantic novel that critiques the British landed gentry at the end of the 18th century, focusing on the turbulent relationship between Elizabeth Bennet and Mr. Darcy.",
    "pageCount": 432,
    "categories": ["Fiction", "Classic"],
    "language": "en",
    "cover": "https://www.crossword.in/cdn/shop/products/714GGM7WK7L.jpg?v=1685357582"
  },
  {
    "title": "The Midnight Library",
    "authors": ["Matt Haig"],
    "publisher": "Viking",
    "publishedDate": "2020-08-13",
    "description": "A novel about choices and regrets, exploring the infinite possibilities of life through the lens of a magical library.",
    "pageCount": 304,
    "categories": ["Fiction", "Fantasy"],
    "language": "en",
    "cover": "https://www.crossword.in/cdn/shop/products/714GGM7WK7L.jpg?v=1685357582"
  },
  {
    "title": "The Henna Artist",
    "authors": ["Alka Joshi"],
    "publisher": "Mira",
    "publishedDate": "2020-03-02",
    "description": "A richly drawn story of love, betrayal, and the journey of a woman finding her place in the world in post-independence India.",
    "pageCount": 368,
    "categories": ["Historical", "Fiction"],
    "language": "en",
    "cover": "https://www.crossword.in/cdn/shop/products/714GGM7WK7L.jpg?v=1685357582"
  }
]
